pwasopt/__init__.py
pwasopt/acquisition.py
pwasopt/categorical_encoder.py
pwasopt/fit_surrogate_pwasp.py
pwasopt/formatCatVar.py
pwasopt/integ_encoder.py
pwasopt/main_pwas.py
pwasopt/main_pwasp.py
pwasopt/pref_fun.py
pwasopt/pref_fun1.py
pwasopt/prob_setup.py
pwasopt/sample.py
pwasopt-0.1.4.dist-info/LICENSE
pwasopt-0.1.4.dist-info/METADATA
pwasopt-0.1.4.dist-info/WHEEL
pwasopt-0.1.4.dist-info/top_level.txt
pwasopt-0.1.4.dist-info/RECORD
