Metadata-Version: 2.1
Name: pwasopt
Version: 0.1.4
Summary: PWAS/PWASp - Global and Preference-based Optimization with Mixed Variables using (P)iece(w)ise (A)ffine (S)urrogates
Author-email: Mengjia Zhu <mengjia.zhu@imtlucca.it>, Alberto Bemporad <alberto.bemporad@imtlucca.it>
Project-URL: Homepage, https://github.com/mjzhu-p/PWAS
Keywords: Mixed-variable optimization,Mixed-integer optimization,global optimization,preference-based optimization,black-box optimization
Classifier: Programming Language :: Python :: 3
Classifier: License :: OSI Approved :: Apache Software License
Classifier: Operating System :: OS Independent
Requires-Python: >=3.7
License-File: LICENSE
Requires-Dist: numpy <2.0.0,>=1.24.3
Requires-Dist: scipy >=1.11.1
Requires-Dist: pulp ==2.8.0
Requires-Dist: pyDOE ==0.3.8
Requires-Dist: scikit-learn ==1.3.0
Requires-Dist: pycddlib <3.0.0,>=2.1.7
Requires-Dist: pyparc >=2.0.4
Requires-Dist: threadpoolctl ==3.1.0
Requires-Dist: cvxopt ==1.2.6
